Metadata-Version: 2.1
Name: chat-client-GB-course-april
Version: 0.1
Summary: Client packet
Author: Andrei Kasyyanyk
Author-email: fantom-gtn@list.ru
